[{"state":{"code":"classDiagram\n    User --> UserDetails\n    User *--  AuthUser\n    UserDetails <|-- AuthUser\n    UserDetails  \"1\" --> \"1\" Salary\n    UserDetails \"1\" --> \"*\" Location\n    UserDetails \"*\" --> \"*\" Flight\n    Flight \"*\" --> \"1\" AirPlane\n    class UserDetails{\n    -Long userId\n    -String firstName\n    -String lastName\n    -String jobTitle\n    -String license\n    -Gender gender\n    -String address\n    -String dateOfBirth\n    -Long totalFlightsHours\n    -Date createdAt\n    +getter-methods()\n    +setter-methods()\n    }\n    class User{\n        -Long userId\n        -String username\n        -String email\n        -String password\n        -Date createdAt\n        -Date updatedAt\n        +getter-methods()\n        +setter-methods()\n    }\n    class Salary{\n    -Long salaryId \n    -String degree \n    -Double basic \n    -Double bonus \n    -Double penalties \n    -Boolean availability \n    -Date createdAt \n    -Date updatedAt \n    +getter-methods()\n    +setter-methods()\n    }\n    class Location{\n    -Long locationId \n    -String ipAddress \n    -String country \n    -String city \n    -String time \n    -String lat \n    -String lng \n    -Boolean isActive=false \n    -Date createdAt \n    -Date updatedAt \n    +getter-methods()\n    +setter-methods()\n    }\n    class Flight{\n    - Long flightId \n    - TripCategory tripCategory \n    - TripType tripType \n    - Boolean showHidden \n    - String departureId \n    - String arrivalId \n    - String duration \n    - String details \n    - String airportTakeOff \n    - String airportTakeOffId \n    - String takeOffTime \n    - String airportLanding \n    - String airportLandingId \n    - String landingTime \n    - Map<Integer,String> stops=new HashMap<>() \n    - List<String> extensions=new ArrayList() \n    - Date outbound_date \n    - Date return_date \n    - String flightNumber \n    -Date createdAt \n    -Date updatedAt \n    +getter-methods()\n    +setter-methods()\n    +addUser(UserDetails user): void\n    +removeUser(UserDetails user): void\n    }\n    class AirPlane{\n    - Long planeId \n    - String companyName \n    - String planeName \n    - String airline \n    - String airlineLogo \n    - String model \n    - Integer totalFlightHours \n    - Integer fuelTankCapacity \n    - Date lastCheckIn \n    - Integer numberOfSeats \n     -Date createdAt \n    -Date updatedAt \n    +getter-methods()\n    +setter-methods()\n    +addFlights(Flight flight):void\n    +removeFlights(Flight flight):void\n    }\n    class AuthUser{\n          - User user\n          + getUser():User\n          + getPassword():String\n          + getUsername():String\n          + isAccountNonExpired():Boolean\n          + isAccountNonLocked():Boolean\n          + isCredentialsNonExpired():Boolean\n    }\n","mermaid":"{\n  \"theme\": \"dark\"\n}","autoSync":true,"rough":false,"updateDiagram":true,"panZoom":true,"editorMode":"code","pan":{"x":321.96807861328125,"y":88.52102661132812},"zoom":0.9331963260946726},"time":1733940092117,"type":"manual","id":"32a0adc4-71f9-45c9-a06d-4d01009e8912","name":"tangy-furniture"},{"state":{"code":"classDiagram\n    User --> UserDetails\n    User *--  AuthUser\n    UserDetails <|-- AuthUser\n    UserDetails  \"1\" --> \"1\" Salary\n    UserDetails \"1\" --> \"*\" Location\n    UserDetails \"*\" --> \"*\" Flight\n    Flight \"*\" --> \"1\" AirPlane\n    class UserDetails{\n    -Long userId\n    -String firstName\n    -String lastName\n    -String jobTitle\n    -String license\n    -Gender gender\n    -String address\n    -String dateOfBirth\n    -Long totalFlightsHours\n    -Date createdAt\n    +getter-methods()\n    +setter-methods()\n    }\n    class User{\n        -Long userId\n        -String username\n        -String email\n        -String password\n        -Date createdAt\n        -Date updatedAt\n        +getter-methods()\n        +setter-methods()\n    }\n    class Salary{\n    -Long salaryId \n    -String degree \n    -Double basic \n    -Double bonus \n    -Double penalties \n    -Boolean availability \n    -Date createdAt \n    -Date updatedAt \n    +getter-methods()\n    +setter-methods()\n    }\n    class Location{\n    -Long locationId \n    -String ipAddress \n    -String country \n    -String city \n    -String time \n    -String lat \n    -String lng \n    -Boolean isActive=false \n    -Date createdAt \n    -Date updatedAt \n    +getter-methods()\n    +setter-methods()\n    }\n    class Flight{\n    - Long flightId \n    - TripCategory tripCategory \n    - TripType tripType \n    - Boolean showHidden \n    - String departureId \n    - String arrivalId \n    - String duration \n    - String details \n    - String airportTakeOff \n    - String airportTakeOffId \n    - String takeOffTime \n    - String airportLanding \n    - String airportLandingId \n    - String landingTime \n    - Map<Integer,String> stops=new HashMap<>() \n    - List<String> extensions=new ArrayList() \n    - Date outbound_date \n    - Date return_date \n    - String flightNumber \n    -Date createdAt \n    -Date updatedAt \n    +getter-methods()\n    +setter-methods()\n    +addUser(UserDetails user): void\n    +removeUser(UserDetails user): void\n    }\n    class AirPlane{\n    - Long planeId \n    - String companyName \n    - String planeName \n    - String airline \n    - String airlineLogo \n    - String model \n    - Integer totalFlightHours \n    - Integer fuelTankCapacity \n    - Date lastCheckIn \n    - Integer numberOfSeats \n     -Date createdAt \n    -Date updatedAt \n    +getter-methods()\n    +setter-methods()\n    +addFlights(Flight flight):void\n    +removeFlights(Flight flight):void\n    }\n    class AuthUser{\n          - User user\n          + getUser():User\n          + getPassword():String\n          + getUsername():String\n          + isAccountNonExpired():Boolean\n          + isAccountNonLocked():Boolean\n          + isCredentialsNonExpired():Boolean\n    }\n","mermaid":"{\n  \"theme\": \"dark\"\n}","autoSync":true,"rough":false,"updateDiagram":true,"panZoom":true,"editorMode":"code","pan":{"x":267.9341735839844,"y":-14.851884841918945},"zoom":1.6532138309016493},"time":1733940083120,"type":"auto","id":"c866af7b-5304-40fd-9f29-e5df56031772","name":"happy-garden"},{"state":{"code":"classDiagram\n    User --> UserDetails\n    AuthUser --|> User\n    UserDetails <|-- AuthUser\n    UserDetails  \"1\" --> \"1\" Salary\n    UserDetails \"1\" --> \"*\" Location\n    UserDetails \"*\" --> \"*\" Flight\n    Flight \"*\" --> \"1\" AirPlane\n    class UserDetails{\n    -Long userId\n    -String firstName\n    -String lastName\n    -String jobTitle\n    -String license\n    -Gender gender\n    -String address\n    -String dateOfBirth\n    -Long totalFlightsHours\n    -Date createdAt\n    +getter-methods()\n    +setter-methods()\n    }\n    class User{\n        -Long userId\n        -String username\n        -String email\n        -String password\n        -Date createdAt\n        -Date updatedAt\n        +getter-methods()\n        +setter-methods()\n    }\n    class Salary{\n    -Long salaryId \n    -String degree \n    -Double basic \n    -Double bonus \n    -Double penalties \n    -Boolean availability \n    -Date createdAt \n    -Date updatedAt \n    +getter-methods()\n    +setter-methods()\n    }\n    class Location{\n    -Long locationId \n    -String ipAddress \n    -String country \n    -String city \n    -String time \n    -String lat \n    -String lng \n    -Boolean isActive=false \n    -Date createdAt \n    -Date updatedAt \n    +getter-methods()\n    +setter-methods()\n    }\n    class Flight{\n    - Long flightId \n    - TripCategory tripCategory \n    - TripType tripType \n    - Boolean showHidden \n    - String departureId \n    - String arrivalId \n    - String duration \n    - String details \n    - String airportTakeOff \n    - String airportTakeOffId \n    - String takeOffTime \n    - String airportLanding \n    - String airportLandingId \n    - String landingTime \n    - Map<Integer,String> stops=new HashMap<>() \n    - List<String> extensions=new ArrayList() \n    - Date outbound_date \n    - Date return_date \n    - String flightNumber \n    -Date createdAt \n    -Date updatedAt \n    +getter-methods()\n    +setter-methods()\n    +addUser(UserDetails user): void\n    +removeUser(UserDetails user): void\n    }\n    class AirPlane{\n    - Long planeId \n    - String companyName \n    - String planeName \n    - String airline \n    - String airlineLogo \n    - String model \n    - Integer totalFlightHours \n    - Integer fuelTankCapacity \n    - Date lastCheckIn \n    - Integer numberOfSeats \n     -Date createdAt \n    -Date updatedAt \n    +getter-methods()\n    +setter-methods()\n    +addFlights(Flight flight):void\n    +removeFlights(Flight flight):void\n    }\n    class AuthUser{\n          - User user\n          + getUser():User\n          + getPassword():String\n          + getUsername():String\n          + isAccountNonExpired():Boolean\n          + isAccountNonLocked():Boolean\n          + isCredentialsNonExpired():Boolean\n    }\n","mermaid":"{\n  \"theme\": \"dark\"\n}","autoSync":true,"rough":false,"updateDiagram":true,"panZoom":true,"editorMode":"code","pan":{"x":210.35525512695312,"y":-125.00685119628906},"zoom":2.420469968593722},"time":1733940023121,"type":"auto","id":"6f3bb37f-73a5-4cd1-a6b6-95bca3a2093a","name":"high-air"},{"state":{"code":"classDiagram\n    User --> UserDetails\n    User --|> AuthUser\n    AuthUser <|-- UserDetails\n    UserDetails  \"1\" --> \"1\" Salary\n    UserDetails \"1\" --> \"*\" Location\n    UserDetails \"*\" --> \"*\" Flight\n    Flight \"*\" --> \"1\" AirPlane\n    class UserDetails{\n    -Long userId\n    -String firstName\n    -String lastName\n    -String jobTitle\n    -String license\n    -Gender gender\n    -String address\n    -String dateOfBirth\n    -Long totalFlightsHours\n    -Date createdAt\n    +getter-methods()\n    +setter-methods()\n    }\n    class User{\n        -Long userId\n        -String username\n        -String email\n        -String password\n        -Date createdAt\n        -Date updatedAt\n        +getter-methods()\n        +setter-methods()\n    }\n    class Salary{\n    -Long salaryId \n    -String degree \n    -Double basic \n    -Double bonus \n    -Double penalties \n    -Boolean availability \n    -Date createdAt \n    -Date updatedAt \n    +getter-methods()\n    +setter-methods()\n    }\n    class Location{\n    -Long locationId \n    -String ipAddress \n    -String country \n    -String city \n    -String time \n    -String lat \n    -String lng \n    -Boolean isActive=false \n    -Date createdAt \n    -Date updatedAt \n    +getter-methods()\n    +setter-methods()\n    }\n    class Flight{\n    - Long flightId \n    - TripCategory tripCategory \n    - TripType tripType \n    - Boolean showHidden \n    - String departureId \n    - String arrivalId \n    - String duration \n    - String details \n    - String airportTakeOff \n    - String airportTakeOffId \n    - String takeOffTime \n    - String airportLanding \n    - String airportLandingId \n    - String landingTime \n    - Map<Integer,String> stops=new HashMap<>() \n    - List<String> extensions=new ArrayList() \n    - Date outbound_date \n    - Date return_date \n    - String flightNumber \n    -Date createdAt \n    -Date updatedAt \n    +getter-methods()\n    +setter-methods()\n    +addUser(UserDetails user): void\n    +removeUser(UserDetails user): void\n    }\n    class AirPlane{\n    - Long planeId \n    - String companyName \n    - String planeName \n    - String airline \n    - String airlineLogo \n    - String model \n    - Integer totalFlightHours \n    - Integer fuelTankCapacity \n    - Date lastCheckIn \n    - Integer numberOfSeats \n     -Date createdAt \n    -Date updatedAt \n    +getter-methods()\n    +setter-methods()\n    +addFlights(Flight flight):void\n    +removeFlights(Flight flight):void\n    }\n    class AuthUser{\n          - User user\n          + getUser():User\n          + getPassword():String\n          + getUsername():String\n          + isAccountNonExpired():Boolean\n          + isAccountNonLocked():Boolean\n          + isCredentialsNonExpired():Boolean\n    }\n","mermaid":"{\n  \"theme\": \"dark\"\n}","autoSync":true,"rough":false,"updateDiagram":true,"panZoom":true,"editorMode":"code","pan":{"x":135.35523986816406,"y":34.9931526184082},"zoom":2.42047000531652},"time":1733939962350,"type":"auto","id":"ab97ba1c-3882-4275-8533-c225a6e1c827","name":"easy-article"},{"state":{"code":"classDiagram\n    User --> UserDetails\n    User --|> AuthUser\n    Au\n    UserDetails  \"1\" --> \"1\" Salary\n    UserDetails \"1\" --> \"*\" Location\n    UserDetails \"*\" --> \"*\" Flight\n    Flight \"*\" --> \"1\" AirPlane\n    class UserDetails{\n    -Long userId\n    -String firstName\n    -String lastName\n    -String jobTitle\n    -String license\n    -Gender gender\n    -String address\n    -String dateOfBirth\n    -Long totalFlightsHours\n    -Date createdAt\n    +getter-methods()\n    +setter-methods()\n    }\n    class User{\n        -Long userId\n        -String username\n        -String email\n        -String password\n        -Date createdAt\n        -Date updatedAt\n        +getter-methods()\n        +setter-methods()\n    }\n    class Salary{\n    -Long salaryId \n    -String degree \n    -Double basic \n    -Double bonus \n    -Double penalties \n    -Boolean availability \n    -Date createdAt \n    -Date updatedAt \n    +getter-methods()\n    +setter-methods()\n    }\n    class Location{\n    -Long locationId \n    -String ipAddress \n    -String country \n    -String city \n    -String time \n    -String lat \n    -String lng \n    -Boolean isActive=false \n    -Date createdAt \n    -Date updatedAt \n    +getter-methods()\n    +setter-methods()\n    }\n    class Flight{\n    - Long flightId \n    - TripCategory tripCategory \n    - TripType tripType \n    - Boolean showHidden \n    - String departureId \n    - String arrivalId \n    - String duration \n    - String details \n    - String airportTakeOff \n    - String airportTakeOffId \n    - String takeOffTime \n    - String airportLanding \n    - String airportLandingId \n    - String landingTime \n    - Map<Integer,String> stops=new HashMap<>() \n    - List<String> extensions=new ArrayList() \n    - Date outbound_date \n    - Date return_date \n    - String flightNumber \n    -Date createdAt \n    -Date updatedAt \n    +getter-methods()\n    +setter-methods()\n    +addUser(UserDetails user): void\n    +removeUser(UserDetails user): void\n    }\n    class AirPlane{\n    - Long planeId \n    - String companyName \n    - String planeName \n    - String airline \n    - String airlineLogo \n    - String model \n    - Integer totalFlightHours \n    - Integer fuelTankCapacity \n    - Date lastCheckIn \n    - Integer numberOfSeats \n     -Date createdAt \n    -Date updatedAt \n    +getter-methods()\n    +setter-methods()\n    +addFlights(Flight flight):void\n    +removeFlights(Flight flight):void\n    }\n    class AuthUser{\n          - User user\n          + getUser():User\n          + getPassword():String\n          + getUsername():String\n          + isAccountNonExpired():Boolean\n          + isAccountNonLocked():Boolean\n          + isCredentialsNonExpired():Boolean\n    }\n","mermaid":"{\n  \"theme\": \"dark\"\n}","autoSync":true,"rough":false,"updateDiagram":false,"panZoom":true,"editorMode":"code","pan":{"x":297.73944091796875,"y":-0.00009497180144535378},"zoom":1.0000002697612418},"time":1733939902349,"type":"auto","id":"c6ad2ea7-0398-415e-9df7-02c60e7b5e08","name":"disgusting-agent"},{"state":{"code":"classDiagram\n    User --> UserDetails\n    \n    UserDetails  \"1\" --> \"1\" Salary\n    UserDetails \"1\" --> \"*\" Location\n    UserDetails \"*\" --> \"*\" Flight\n    Flight \"*\" --> \"1\" AirPlane\n    class UserDetails{\n    -Long userId\n    -String firstName\n    -String lastName\n    -String jobTitle\n    -String license\n    -Gender gender\n    -String address\n    -String dateOfBirth\n    -Long totalFlightsHours\n    -Date createdAt\n    +getter-methods()\n    +setter-methods()\n    }\n    class User{\n        -Long userId\n        -String username\n        -String email\n        -String password\n        -Date createdAt\n        -Date updatedAt\n        +getter-methods()\n        +setter-methods()\n    }\n    class Salary{\n    -Long salaryId \n    -String degree \n    -Double basic \n    -Double bonus \n    -Double penalties \n    -Boolean availability \n    -Date createdAt \n    -Date updatedAt \n    +getter-methods()\n    +setter-methods()\n    }\n    class Location{\n    -Long locationId \n    -String ipAddress \n    -String country \n    -String city \n    -String time \n    -String lat \n    -String lng \n    -Boolean isActive=false \n    -Date createdAt \n    -Date updatedAt \n    +getter-methods()\n    +setter-methods()\n    }\n    class Flight{\n    - Long flightId \n    - TripCategory tripCategory \n    - TripType tripType \n    - Boolean showHidden \n    - String departureId \n    - String arrivalId \n    - String duration \n    - String details \n    - String airportTakeOff \n    - String airportTakeOffId \n    - String takeOffTime \n    - String airportLanding \n    - String airportLandingId \n    - String landingTime \n    - Map<Integer,String> stops=new HashMap<>() \n    - List<String> extensions=new ArrayList() \n    - Date outbound_date \n    - Date return_date \n    - String flightNumber \n    -Date createdAt \n    -Date updatedAt \n    +getter-methods()\n    +setter-methods()\n    +addUser(UserDetails user): void\n    +removeUser(UserDetails user): void\n    }\n    class AirPlane{\n    - Long planeId \n    - String companyName \n    - String planeName \n    - String airline \n    - String airlineLogo \n    - String model \n    - Integer totalFlightHours \n    - Integer fuelTankCapacity \n    - Date lastCheckIn \n    - Integer numberOfSeats \n     -Date createdAt \n    -Date updatedAt \n    +getter-methods()\n    +setter-methods()\n    +addFlights(Flight flight):void\n    +removeFlights(Flight flight):void\n    }\n    class AuthUser{\n          - User user\n          + getUser():User\n          + getPassword():String\n          + getUsername():String\n          + isAccountNonExpired():Boolean\n          + isAccountNonLocked():Boolean\n          + isCredentialsNonExpired():Boolean\n    }\n","mermaid":"{\n  \"theme\": \"dark\"\n}","autoSync":true,"rough":false,"updateDiagram":true,"panZoom":true,"editorMode":"code","pan":{"x":297.73944091796875,"y":-0.00009497180144535378},"zoom":1.0000002697612418},"time":1733939842273,"type":"auto","id":"be9e832e-37f6-45e5-8dee-69b242cd5f79","name":"odd-telephone"},{"state":{"code":"classDiagram\n    User --> UserDetails\n    UserDetails  \"1\" --> \"1\" Salary\n    UserDetails \"1\" --> \"*\" Location\n    UserDetails \"*\" --> \"*\" Flight\n    Flight \"*\" --> \"1\" AirPlane\n    class UserDetails{\n    -Long userId\n    -String firstName\n    -String lastName\n    -String jobTitle\n    -String license\n    -Gender gender\n    -String address\n    -String dateOfBirth\n    -Long totalFlightsHours\n    -Date createdAt\n    +getter-methods()\n    +setter-methods()\n    }\n    class User{\n        -Long userId\n        -String username\n        -String email\n        -String password\n        -Date createdAt\n        -Date updatedAt\n        +getter-methods()\n        +setter-methods()\n    }\n    class Salary{\n    -Long salaryId \n    -String degree \n    -Double basic \n    -Double bonus \n    -Double penalties \n    -Boolean availability \n    -Date createdAt \n    -Date updatedAt \n    +getter-methods()\n    +setter-methods()\n    }\n    class Location{\n    -Long locationId \n    -String ipAddress \n    -String country \n    -String city \n    -String time \n    -String lat \n    -String lng \n    -Boolean isActive=false \n    -Date createdAt \n    -Date updatedAt \n    +getter-methods()\n    +setter-methods()\n    }\n    class Flight{\n    - Long flightId \n    - TripCategory tripCategory \n    - TripType tripType \n    - Boolean showHidden \n    - String departureId \n    - String arrivalId \n    - String duration \n    - String details \n    - String airportTakeOff \n    - String airportTakeOffId \n    - String takeOffTime \n    - String airportLanding \n    - String airportLandingId \n    - String landingTime \n    - Map<Integer,String> stops=new HashMap<>() \n    - List<String> extensions=new ArrayList() \n    - Date outbound_date \n    - Date return_date \n    - String flightNumber \n    -Date createdAt \n    -Date updatedAt \n    +getter-methods()\n    +setter-methods()\n    +addUser(UserDetails user): void\n    +removeUser(UserDetails user): void\n    }\n    class AirPlane{\n    - Long planeId \n    - String companyName \n    - String planeName \n    - String airline \n    - String airlineLogo \n    - String model \n    - Integer totalFlightHours \n    - Integer fuelTankCapacity \n    - Date lastCheckIn \n    - Integer numberOfSeats \n     -Date createdAt \n    -Date updatedAt \n    +getter-methods()\n    +setter-methods()\n    +addFlights(Flight flight):void\n    +removeFlights(Flight flight):void\n    }\n    class AuthUser{\n          - User user\n          + getUser():User\n          + getPassword():String\n          + getUsername():String\n          + isAccountNonExpired():Boolean\n          \n    }\n","mermaid":"{\n  \"theme\": \"dark\"\n}","autoSync":true,"rough":false,"updateDiagram":false,"panZoom":true,"editorMode":"code","pan":{"x":297.73944091796875,"y":-0.00009497180144535378},"zoom":1.0000002697612418},"time":1733939781739,"type":"auto","id":"9df91318-024f-483a-bea5-32b755afdb91","name":"refined-daybreak"},{"state":{"code":"classDiagram\n    User --> UserDetails\n    UserDetails  \"1\" --> \"1\" Salary\n    UserDetails \"1\" --> \"*\" Location\n    UserDetails \"*\" --> \"*\" Flight\n    Flight \"*\" --> \"1\" AirPlane\n    class UserDetails{\n    -Long userId\n    -String firstName\n    -String lastName\n    -String jobTitle\n    -String license\n    -Gender gender\n    -String address\n    -String dateOfBirth\n    -Long totalFlightsHours\n    -Date createdAt\n    +getter-methods()\n    +setter-methods()\n    }\n    class User{\n        -Long userId\n        -String username\n        -String email\n        -String password\n        -Date createdAt\n        -Date updatedAt\n        +getter-methods()\n        +setter-methods()\n    }\n    class Salary{\n    -Long salaryId \n    -String degree \n    -Double basic \n    -Double bonus \n    -Double penalties \n    -Boolean availability \n    -Date createdAt \n    -Date updatedAt \n    +getter-methods()\n    +setter-methods()\n    }\n    class Location{\n    -Long locationId \n    -String ipAddress \n    -String country \n    -String city \n    -String time \n    -String lat \n    -String lng \n    -Boolean isActive=false \n    -Date createdAt \n    -Date updatedAt \n    +getter-methods()\n    +setter-methods()\n    }\n    class Flight{\n    - Long flightId \n    - TripCategory tripCategory \n    - TripType tripType \n    - Boolean showHidden \n    - String departureId \n    - String arrivalId \n    - String duration \n    - String details \n    - String airportTakeOff \n    - String airportTakeOffId \n    - String takeOffTime \n    - String airportLanding \n    - String airportLandingId \n    - String landingTime \n    - Map<Integer,String> stops=new HashMap<>() \n    - List<String> extensions=new ArrayList() \n    - Date outbound_date \n    - Date return_date \n    - String flightNumber \n    -Date createdAt \n    -Date updatedAt \n    +getter-methods()\n    +setter-methods()\n    +addUser(UserDetails user): void\n    +removeUser(UserDetails user): void\n    }\n    class AirPlane{\n    - Long planeId \n    - String companyName \n    - String planeName \n    - String airline \n    - String airlineLogo \n    - String model \n    - Integer totalFlightHours \n    - Integer fuelTankCapacity \n    - Date lastCheckIn \n    - Integer numberOfSeats \n     -Date createdAt \n    -Date updatedAt \n    +getter-methods()\n    +setter-methods()\n    +addFlights(Flight flight):void\n    +removeFlights(Flight flight):void\n    }\n    class AuthUser{\n          - User user\n          +User getUser()\n    }\n","mermaid":"{\n  \"theme\": \"dark\"\n}","autoSync":true,"rough":false,"updateDiagram":true,"panZoom":true,"editorMode":"code","pan":{"x":297.73944091796875,"y":-0.00009497180144535378},"zoom":1.0000002697612418},"time":1733939721711,"type":"auto","id":"13e844df-3f25-4c22-9d13-35f96f518457","name":"mammoth-jewellery"},{"state":{"code":"classDiagram\n    User --> UserDetails\n    UserDetails  \"1\" --> \"1\" Salary\n    UserDetails \"1\" --> \"*\" Location\n    UserDetails \"*\" --> \"*\" Flight\n    Flight \"*\" --> \"1\" AirPlane\n    class UserDetails{\n    -Long userId\n    -String firstName\n    -String lastName\n    -String jobTitle\n    -String license\n    -Gender gender\n    -String address\n    -String dateOfBirth\n    -Long totalFlightsHours\n    -Date createdAt\n    +getter-methods()\n    +setter-methods()\n    }\n    class User{\n        -Long userId\n        -String username\n        -String email\n        -String password\n        -Date createdAt\n        -Date updatedAt\n        +getter-methods()\n        +setter-methods()\n    }\n    class Salary{\n    -Long salaryId \n    -String degree \n    -Double basic \n    -Double bonus \n    -Double penalties \n    -Boolean availability \n    -Date createdAt \n    -Date updatedAt \n    +getter-methods()\n    +setter-methods()\n    }\n    class Location{\n    -Long locationId \n    -String ipAddress \n    -String country \n    -String city \n    -String time \n    -String lat \n    -String lng \n    -Boolean isActive=false \n    -Date createdAt \n    -Date updatedAt \n    +getter-methods()\n    +setter-methods()\n    }\n    class Flight{\n    - Long flightId \n    - TripCategory tripCategory \n    - TripType tripType \n    - Boolean showHidden \n    - String departureId \n    - String arrivalId \n    - String duration \n    - String details \n    - String airportTakeOff \n    - String airportTakeOffId \n    - String takeOffTime \n    - String airportLanding \n    - String airportLandingId \n    - String landingTime \n    - Map<Integer,String> stops=new HashMap<>() \n    - List<String> extensions=new ArrayList() \n    - Date outbound_date \n    - Date return_date \n    - String flightNumber \n    -Date createdAt \n    -Date updatedAt \n    +getter-methods()\n    +setter-methods()\n    +addUser(UserDetails user): void\n    +removeUser(UserDetails user): void\n    }\n    class AirPlane{\n    - Long planeId \n    - String companyName \n    - String planeName \n    - String airline \n    - String airlineLogo \n    - String model \n    - Integer totalFlightHours \n    - Integer fuelTankCapacity \n    - Date lastCheckIn \n    - Integer numberOfSeats \n     -Date createdAt \n    -Date updatedAt \n    +getter-methods()\n    +setter-methods()\n    +addFlights(Flight flight):void\n    +removeFlights(Flight flight):void\n    }\n\n","mermaid":"{\n  \"theme\": \"dark\"\n}","autoSync":true,"rough":false,"updateDiagram":true,"panZoom":true,"editorMode":"code","pan":{"x":297.73944091796875,"y":-0.00009497180144535378},"zoom":1.0000002697612418},"time":1733939661714,"type":"auto","id":"4ecafd8c-7c1b-4fd8-a7b3-20587344e30c","name":"rough-angle"},{"state":{"code":"classDiagram\n    UserDetails  \"1\" --> \"1\" Salary\n    UserDetails \"1\" --> \"*\" Location\n    UserDetails \"*\" --> \"*\" Flight\n    User <|-- UserDetails\n    Flight \"*\" --> \"1\" AirPlane\n    class UserDetails{\n    -Long userId\n    -String firstName\n    -String lastName\n    -String jobTitle\n    -String license\n    -Gender gender\n    -String address\n    -String dateOfBirth\n    -Long totalFlightsHours\n    -Date createdAt\n    +getter-methods()\n    +setter-methods()\n    }\n    class User{\n        -Long userId\n        -String username\n        -String email\n        -String password\n        -Date createdAt\n        -Date updatedAt\n        +getter-methods()\n        +setter-methods()\n    }\n    class Salary{\n    -Long salaryId \n    -String degree \n    -Double basic \n    -Double bonus \n    -Double penalties \n    -Boolean availability \n    -Date createdAt \n    -Date updatedAt \n    +getter-methods()\n    +setter-methods()\n    }\n    class Location{\n    -Long locationId \n    -String ipAddress \n    -String country \n    -String city \n    -String time \n    -String lat \n    -String lng \n    -Boolean isActive=false \n    -Date createdAt \n    -Date updatedAt \n    +getter-methods()\n    +setter-methods()\n    }\n    class Flight{\n    - Long flightId \n    - TripCategory tripCategory \n    - TripType tripType \n    - Boolean showHidden \n    - String departureId \n    - String arrivalId \n    - String duration \n    - String details \n    - String airportTakeOff \n    - String airportTakeOffId \n    - String takeOffTime \n    - String airportLanding \n    - String airportLandingId \n    - String landingTime \n    - Map<Integer,String> stops=new HashMap<>() \n    - List<String> extensions=new ArrayList() \n    - Date outbound_date \n    - Date return_date \n    - String flightNumber \n    -Date createdAt \n    -Date updatedAt \n    +getter-methods()\n    +setter-methods()\n    +addUser(UserDetails user): void\n    +removeUser(UserDetails user): void\n    }\n    class AirPlane{\n    - Long planeId \n    - String companyName \n    - String planeName \n    - String airline \n    - String airlineLogo \n    - String model \n    - Integer totalFlightHours \n    - Integer fuelTankCapacity \n    - Date lastCheckIn \n    - Integer numberOfSeats \n     -Date createdAt \n    -Date updatedAt \n    +getter-methods()\n    +setter-methods()\n    +addFlights(Flight flight):void\n    +removeFlights(Flight flight):void\n    }\n\n","mermaid":"{\n  \"theme\": \"dark\"\n}","autoSync":true,"rough":false,"updateDiagram":true,"panZoom":true,"editorMode":"code","pan":{"x":297.73944091796875,"y":-0.00009497180144535378},"zoom":1.0000002697612418},"time":1733939601712,"type":"auto","id":"0275304b-22c0-4063-abb1-09430f06f231","name":"wrong-author"},{"state":{"code":"classDiagram\n    UserDetails  \"1\" --> \"1\" Salary\n    UserDetails \"1\" --> \"*\" Location\n    UserDetails \"*\" --> \"*\" Flight\n    User <|-- UserDetails\n    Flight \"*\" --> \"1\" AirPlane\n    class UserDetails{\n    -Long userId\n    -String firstName\n    -String lastName\n    -String jobTitle\n    -String license\n    -Gender gender\n    -String address\n    -String dateOfBirth\n    -Long totalFlightsHours\n    -Date createdAt\n    +getter-methods()\n    +setter-methods()\n    }\n    class User{\n        -Long userId\n        -String username\n        -String email\n        -String password\n        -Date createdAt\n        -Date updatedAt\n        +getter-methods()\n        +setter-methods()\n    }\n    class Salary{\n    -Long salaryId \n    -String degree \n    -Double basic \n    -Double bonus \n    -Double penalties \n    -Boolean availability \n    -Date createdAt \n    -Date updatedAt \n    +getter-methods()\n    +setter-methods()\n    }\n    class Location{\n    -Long locationId \n    -String ipAddress \n    -String country \n    -String city \n    -String time \n    -String lat \n    -String lng \n    -Boolean isActive=false \n    -Date createdAt \n    -Date updatedAt \n    +getter-methods()\n    +setter-methods()\n    }\n    class Flight{\n    - Long flightId \n    - TripCategory tripCategory \n    - TripType tripType \n    - Boolean showHidden \n    - String departureId \n    - String arrivalId \n    - String duration \n    - String details \n    - String airportTakeOff \n    - String airportTakeOffId \n    - String takeOffTime \n    - String airportLanding \n    - String airportLandingId \n    - String landingTime \n    - Map<Integer,String> stops=new HashMap<>() \n    - List<String> extensions=new ArrayList() \n    - Date outbound_date \n    - Date return_date \n    - String flightNumber \n    -Date createdAt \n    -Date updatedAt \n    +getter-methods()\n    +setter-methods()\n    +addUser(UserDetails user): void\n    +removeUser(UserDetails user): void\n    }\n    class AirPlane{\n    - Long planeId \n    - String companyName \n    - String planeName \n    - String airline \n    - String airlineLogo \n    - String model \n    - Integer totalFlightHours \n    - Integer fuelTankCapacity \n    - Date lastCheckIn \n    - Integer numberOfSeats \n     -Date createdAt \n    -Date updatedAt \n    +getter-methods()\n    +setter-methods()\n    +addFlights(Flight flight):void\n    +removeFlights(Flight flight):void\n    }\n\n","mermaid":"{\n  \"theme\": \"dark\"\n}","autoSync":true,"rough":false,"updateDiagram":true,"panZoom":true,"editorMode":"code"},"time":1733939361711,"type":"auto","id":"4ea8cb40-f9ed-4388-b80a-8a8ff5664187","name":"polite-library"},{"state":{"code":"classDiagram\n    UserDetails  \"1\" --> \"1\" Salary\n    UserDetails \"1\" --> \"*\" Location\n    UserDetails \"*\" --> \"*\" Flight\n    User <|-- UserDetails\n\n    class UserDetails{\n    -Long userId\n    -String firstName\n    -String lastName\n    -String jobTitle\n    -String license\n    -Gender gender\n    -String address\n    -String dateOfBirth\n    -Long totalFlightsHours\n    -Date createdAt\n    +getter-methods()\n    +setter-methods()\n    }\n    class User{\n        -Long userId\n        -String username\n        -String email\n        -String password\n        -Date createdAt\n        -Date updatedAt\n        +getter-methods()\n        +setter-methods()\n    }\n    class Salary{\n    -Long salaryId \n    -String degree \n    -Double basic \n    -Double bonus \n    -Double penalties \n    -Boolean availability \n    -Date createdAt \n    -Date updatedAt \n    +getter-methods()\n    +setter-methods()\n    }\n    class Location{\n    -Long locationId \n    -String ipAddress \n    -String country \n    -String city \n    -String time \n    -String lat \n    -String lng \n    -Boolean isActive=false \n    -Date createdAt \n    -Date updatedAt \n    +getter-methods()\n    +setter-methods()\n    }\n    class Flight{\n    - Long flightId \n    - TripCategory tripCategory \n    - TripType tripType \n    - Boolean showHidden \n    - String departureId \n    - String arrivalId \n    - String duration \n    - String details \n    - String airportTakeOff \n    - String airportTakeOffId \n    - String takeOffTime \n    - String airportLanding \n    - String airportLandingId \n    - String landingTime \n    - Map<Integer,String> stops=new HashMap<>() \n    - List<String> extensions=new ArrayList() \n    - Date outbound_date \n    - Date return_date \n    - String flightNumber \n    -Date createdAt \n    -Date updatedAt \n    +getter-methods()\n    +setter-methods()\n    +addUser(UserDetails user): void\n    +removeUser(UserDetails user): void\n    }\n    class AirPlane{\n    - Long planeId \n    - String companyName \n    - String planeName \n    - String airline \n    - String airlineLogo \n    - String model \n    - Integer totalFlightHours \n    - Integer fuelTankCapacity \n    - Date lastCheckIn \n    - Integer numberOfSeats \n     -Date createdAt \n    -Date updatedAt \n    +getter-methods()\n    +setter-methods()\n    +addFlights(Flight flight):void\n    +removeFlights(Flight flight):void\n    }\n\n","mermaid":"{\n  \"theme\": \"dark\"\n}","autoSync":true,"rough":false,"updateDiagram":true,"panZoom":true,"editorMode":"code"},"time":1733939301710,"type":"auto","id":"c7375c4f-9b39-4e95-987a-8ce22beec3ee","name":"ambitious-engine"},{"state":{"code":"classDiagram\n    UserDetails  \"1\" --> \"1\" Salary\n    UserDetails \"1\" --> \"*\" Location\n    UserDetails \"*\" --> \"*\" Flight\n    User <|-- UserDetails\n\n    class UserDetails{\n    -Long userId\n    -String firstName\n    -String lastName\n    -String jobTitle\n    -String license\n    -Gender gender\n    -String address\n    -String dateOfBirth\n    -Long totalFlightsHours\n    -Date createdAt\n    +getter-methods()\n    +setter-methods()\n    }\n    class User{\n        -Long userId\n        -String username\n        -String email\n        -String password\n        -Date createdAt\n        -Date updatedAt\n        +getter-methods()\n        +setter-methods()\n    }\n    class Salary{\n    -Long salaryId \n    -String degree \n    -Double basic \n    -Double bonus \n    -Double penalties \n    -Boolean availability \n    -Date createdAt \n    -Date updatedAt \n    +getter-methods()\n    +setter-methods()\n    }\n    class Location{\n    -Long locationId \n    -String ipAddress \n    -String country \n    -String city \n    -String time \n    -String lat \n    -String lng \n    -Boolean isActive=false \n    -Date createdAt \n    -Date updatedAt \n    +getter-methods()\n    +setter-methods()\n    }\n    class Flight{\n    - Long flightId \n    - TripCategory tripCategory \n    - TripType tripType \n    - Boolean showHidden \n    - String departureId \n    - String arrivalId \n    - String duration \n    - String details \n    - String airportTakeOff \n    - String airportTakeOffId \n    - String takeOffTime \n    - String airportLanding \n    - String airportLandingId \n    - String landingTime \n    - Map<Integer,String> stops=new HashMap<>() \n    - List<String> extensions=new ArrayList() \n    - Date outbound_date \n    - Date return_date \n    - String flightNumber \n    -Date createdAt \n    -Date updatedAt \n    +getter-methods()\n    +setter-methods()\n    +addUser(UserDetails user): void\n    +removeUser(UserDetails user): void\n    }\n    class AirPlane{\n    - Long planeId;\n    - String companyName;\n    - String planeName;\n    - String airline;\n    - String airlineLogo;\n    - String model;\n    - Integer totalFlightHours;\n    - Integer fuelTankCapacity;\n    - Date lastCheckIn;\n    - Integer numberOfSeats;\n    \n    }\n\n","mermaid":"{\n  \"theme\": \"dark\"\n}","autoSync":true,"rough":false,"updateDiagram":true,"panZoom":true,"editorMode":"code"},"time":1733939241704,"type":"auto","id":"b37f6e2f-21dc-478a-88c9-527a5718acdf","name":"boring-pencil"},{"state":{"code":"classDiagram\n    UserDetails  \"1\" --> \"1\" Salary\n    UserDetails \"1\" --> \"*\" Location\n    UserDetails \"*\" --> \"*\" Flight\n    \n    class UserDetails{\n    -Long userId\n    -String firstName\n    -String lastName\n    -String jobTitle\n    -String license\n    -Gender gender\n    -String address\n    -String dateOfBirth\n    -Long totalFlightsHours\n    -Date createdAt\n    +getter-methods()\n    +setter-methods()\n    }\n    class User{\n        -Long userId\n        -String username\n        -String email\n        -String password\n        -Date createdAt\n        -Date updatedAt\n        +getter-methods()\n        +setter-methods()\n    }\n    class Salary{\n    -Long salaryId \n    -String degree \n    -Double basic \n    -Double bonus \n    -Double penalties \n    -Boolean availability \n    -Date createdAt \n    -Date updatedAt \n    +getter-methods()\n    +setter-methods()\n    }\n    class Location{\n    -Long locationId \n    -String ipAddress \n    -String country \n    -String city \n    -String time \n    -String lat \n    -String lng \n    -Boolean isActive=false \n    -Date createdAt \n    -Date updatedAt \n    +getter-methods()\n    +setter-methods()\n    }\n    class Flight{\n    - Long flightId \n    - TripCategory tripCategory \n    - TripType tripType \n    - Boolean showHidden \n    - String departureId \n    - String arrivalId \n    - String duration \n    - String details \n    - String airportTakeOff \n    - String airportTakeOffId \n    - String takeOffTime \n    - String airportLanding \n    - String airportLandingId \n    - String landingTime \n    - Map<Integer,String> stops=new HashMap<>() \n    - List<String> extensions=new ArrayList() \n    - Date outbound_date \n    - Date return_date \n    - String flightNumber \n    -Date createdAt \n    -Date updatedAt \n    +getter-methods()\n    +setter-methods()\n    +addUser(UserDetails user): void\n    +removeUser(UserDetails user): void\n    }\n\n","mermaid":"{\n  \"theme\": \"dark\"\n}","autoSync":true,"rough":false,"updateDiagram":false,"panZoom":true,"editorMode":"code"},"time":1733939181623,"type":"auto","id":"288b4bd7-9c24-41bd-966f-e33eac6b8299","name":"cool-nail"},{"state":{"code":"classDiagram\n    User <|-- UserDetails\n    UserDetails  \"1\" --> \"1\" Salary\n    UserDetails \"1\" --> \"*\" Location\n    UserDetails \"*\" --> \"*\" Flight\n    class UserDetails{\n    -Long userId\n    -String firstName\n    -String lastName\n    -String jobTitle\n    -String license\n    -Gender gender\n    -String address\n    -String dateOfBirth\n    -Long totalFlightsHours\n    -Date createdAt\n    +getter-methods()\n    +setter-methods()\n    }\n    class User{\n        -Long userId\n        -String username\n        -String email\n        -String password\n        -Date createdAt\n        -Date updatedAt\n        +getter-methods()\n        +setter-methods()\n    }\n    class Salary{\n    -Long salaryId \n    -String degree \n    -Double basic \n    -Double bonus \n    -Double penalties \n    -Boolean availability \n    -Date createdAt \n    -Date updatedAt \n    +getter-methods()\n    +setter-methods()\n    }\n    class Location{\n    -Long locationId \n    -String ipAddress \n    -String country \n    -String city \n    -String time \n    -String lat \n    -String lng \n    -Boolean isActive=false \n    -Date createdAt \n    -Date updatedAt \n    +getter-methods()\n    +setter-methods()\n    }\n    class Flight{\n    - Long flightId \n    - TripCategory tripCategory \n    - TripType tripType \n    - Boolean showHidden \n    - String departureId \n    - String arrivalId \n    - String duration \n    - String details \n    - String airportTakeOff \n    - String airportTakeOffId \n    - String takeOffTime \n    - String airportLanding \n    - String airportLandingId \n    - String landingTime \n    - Map<Integer,String> stops=new HashMap<>() \n    - List<String> extensions=new ArrayList() \n    - Date outbound_date \n    - Date return_date \n    - String flightNumber \n    -Date createdAt \n    -Date updatedAt \n    +getter-methods()\n    +setter-methods()\n    +addUser(UserDetails user): void\n    +removeUser(UserDetails user): void\n    }\n\n","mermaid":"{\n  \"theme\": \"dark\"\n}","autoSync":true,"rough":false,"updateDiagram":true,"panZoom":true,"editorMode":"code"},"time":1733935843303,"type":"auto","id":"421c3e6e-c5fa-47ed-aab1-51568b9ab2b9","name":"cold-actor"},{"state":{"code":"classDiagram\n    User <|-- UserDetails\n    User  \"1\" --> \"1\" Salary\n    UserDetails \"1\" --> \"*\" Location\n    class UserDetails{\n    -Long userId\n    -String firstName\n    -String lastName\n    -String jobTitle\n    -String license\n    -Gender gender\n    -String address\n    -String dateOfBirth\n    -Long totalFlightsHours\n    -Date createdAt\n    +getter-methods()\n    +setter-methods()\n    }\n    class User{\n        -Long userId\n        -String username\n        -String email\n        -String password\n        -Date createdAt\n        -Date updatedAt\n        +getter-methods()\n        +setter-methods()\n    }\n    class Salary{\n    -Long salaryId \n    -String degree \n    -Double basic \n    -Double bonus \n    -Double penalties \n    -Boolean availability \n    -Date createdAt \n    -Date updatedAt \n    +getter-methods()\n    +setter-methods()\n    }\n    class Location{\n    -Long locationId \n    -String ipAddress \n    -String country \n    -String city \n    -String time \n    -String lat \n    -String lng \n    -Boolean isActive=false \n    -Date createdAt \n    -Date updatedAt \n    +getter-methods()\n    +setter-methods()\n    }\n    class Flight{\n    - Long flightId \n    - TripCategory tripCategory \n    - TripType tripType \n    - Boolean showHidden \n    - String departureId \n    - String arrivalId \n    - String duration \n    - String details \n    - String airportTakeOff \n    - String airportTakeOffId \n    - String takeOffTime \n    - String airportLanding \n    - String airportLandingId \n    - String landingTime \n    - Map<Integer,String> stops=new HashMap<>() \n    - List<String> extensions=new ArrayList() \n    - Date outbound_date \n    - Date return_date \n    - String flightNumber \n    -Date createdAt \n    -Date updatedAt \n    +getter-methods()\n    +setter-methods()\n    +addUser(UserDetails user): void\n    +removeUser(UserDetails user)@\n    }\n\n","mermaid":"{\n  \"theme\": \"dark\"\n}","autoSync":true,"rough":false,"updateDiagram":false,"panZoom":true,"editorMode":"code"},"time":1733935783300,"type":"auto","id":"dd622886-e7ac-487d-9be1-686817c9f960","name":"thundering-river"},{"state":{"code":"classDiagram\n    User <|-- UserDetails\n    User  \"1\" --> \"1\" Salary\n    UserDetails \"1\" --> \"*\" Location\n    class UserDetails{\n    -Long userId\n    -String firstName\n    -String lastName\n    -String jobTitle\n    -String license\n    -Gender gender\n    -String address\n    -String dateOfBirth\n    -Long totalFlightsHours\n    -Date createdAt\n    +getter-methods()\n    +setter-methods()\n    }\n    class User{\n        -Long userId\n        -String username\n        -String email\n        -String password\n        -Date createdAt\n        -Date updatedAt\n        +getter-methods()\n        +setter-methods()\n    }\n    class Salary{\n    -Long salaryId \n    -String degree \n    -Double basic \n    -Double bonus \n    -Double penalties \n    -Boolean availability \n    -Date createdAt \n    -Date updatedAt \n    +getter-methods()\n    +setter-methods()\n    }\n    class Location{\n    -Long locationId \n    -String ipAddress \n    -String country \n    -String city \n    -String time \n    -String lat \n    -String lng \n    -Boolean isActive=false \n    -Date createdAt \n    -Date updatedAt \n    +getter-methods()\n    +setter-methods()\n    }\n    class Flight{\n    - Long flightId \n    - TripCategory tripCategory \n    - TripType tripType \n    - Boolean showHidden \n    - String departureId \n    - String arrivalId \n    - String duration \n    - String details \n    - String airportTakeOff \n    - String airportTakeOffId \n    - String takeOffTime \n    - String airportLanding \n    - String airportLandingId \n    - String landingTime \n    - Map<Integer,String> stops=new HashMap<>() \n    - List<String> extensions=new ArrayList() \n    - Date outbound_date \n    - Date return_date \n    - String flightNumber \n    -\n    }\n\n","mermaid":"{\n  \"theme\": \"dark\"\n}","autoSync":true,"rough":false,"updateDiagram":false,"panZoom":true,"editorMode":"code"},"time":1733935723299,"type":"auto","id":"54d04119-0e81-48e1-ab66-1638b78c1bc5","name":"ashamed-yak"},{"state":{"code":"classDiagram\n    User <|-- UserDetails\n    User  \"1\" --> \"1\" Salary\n    UserDetails \"1\" --> \"*\" Location\n    class UserDetails{\n    -Long userId\n    -String firstName\n    -String lastName\n    -String jobTitle\n    -String license\n    -Gender gender\n    -String address\n    -String dateOfBirth\n    -Long totalFlightsHours\n    -Date createdAt\n    +getter-methods()\n    +setter-methods()\n    }\n    class User{\n        -Long userId\n        -String username\n        -String email\n        -String password\n        -Date createdAt\n        -Date updatedAt\n        +getter-methods()\n        +setter-methods()\n    }\n    class Salary{\n    -Long salaryId \n    -String degree \n    -Double basic \n    -Double bonus \n    -Double penalties \n    -Boolean availability \n    -Date createdAt \n    -Date updatedAt \n    +getter-methods()\n    +setter-methods()\n    }\n    class Location{\n    -Long locationId \n    -String ipAddress \n    -String country \n    -String city \n    -String time \n    -String lat \n    -String lng \n    -Boolean isActive=false \n    -Date createdAt \n    -Date updatedAt \n    +getter-methods()\n    +setter-methods()\n    }\n    class Flight{\n    private Long flightId;\n    private TripCategory tripCategory;\n    private TripType tripType;\n    private Boolean showHidden;\n    @Column(nullable = false)\n    private String departureId;\n    @Column(nullable = false)\n    private String arrivalId;\n    @Column(nullable = false)\n    private String duration;\n    private String details;\n    private String airportTakeOff;\n    private String airportTakeOffId;\n    private String takeOffTime;\n    private String airportLanding;\n    private String airportLandingId;\n    private String landingTime;\n    \n    }\n\n","mermaid":"{\n  \"theme\": \"dark\"\n}","autoSync":true,"rough":false,"updateDiagram":true,"panZoom":true,"editorMode":"code"},"time":1733935663300,"type":"auto","id":"cb250382-48cb-4fad-8046-96918fad0aff","name":"pitiful-balloon"},{"state":{"code":"classDiagram\n    User <|-- UserDetails\n    User  \"1\" --> \"1\" Salary\n    UserDetails \"1\" --> \"*\" Location\n    class UserDetails{\n    -Long userId\n    -String firstName\n    -String lastName\n    -String jobTitle\n    -String license\n    -Gender gender\n    -String address\n    -String dateOfBirth\n    -Long totalFlightsHours\n    -Date createdAt\n    +getter-methods()\n    +setter-methods()\n    }\n    class User{\n        -Long userId\n        -String username\n        -String email\n        -String password\n        -Date createdAt\n        -Date updatedAt\n        +getter-methods()\n        +setter-methods()\n    }\n    class Salary{\n    -Long salaryId \n    -String degree \n    -Double basic \n    -Double bonus \n    -Double penalties \n    -Boolean availability \n    -Date createdAt \n    -Date updatedAt \n    +getter-methods()\n    +setter-methods()\n    }\n    class Location{\n    -Long locationId \n    -String ipAddress \n    -String country \n    -String city \n    -String time \n    -String lat \n    -String lng \n    -Boolean isActive=false \n    -Date createdAt \n    -Date updatedAt \n    +getter-methods()\n    +setter-methods()\n    }\n\n\n","mermaid":"{\n  \"theme\": \"dark\"\n}","autoSync":true,"rough":false,"updateDiagram":true,"panZoom":true,"editorMode":"code"},"time":1733935603300,"type":"auto","id":"4d4abb16-a1c6-47d7-a1f7-63281afcc266","name":"big-crayon"},{"state":{"code":"classDiagram\n    User <|-- UserDetails\n    User  \"1\" --> \"1\" Salary\n    class UserDetails{\n    -Long userId\n    -String firstName\n    -String lastName\n    -String jobTitle\n    -String license\n    -Gender gender\n    -String address\n    -String dateOfBirth\n    -Long totalFlightsHours\n    -Date createdAt\n    +getter-methods()\n    +setter-methods()\n    }\n    class User{\n        -Long userId\n        -String username\n        -String email\n        -String password\n        -Date createdAt\n        -Date updatedAt\n        +getter-methods()\n        +setter-methods()\n    }\n    class Salary{\n    -Long salaryId \n    -String degree \n    -Double basic \n    -Double bonus \n    -Double penalties \n    -Boolean availability \n    -Date createdAt \n    -Date updatedAt \n    +getter-methods()\n    +setter-methods()\n    }\n    class Location{\n    -Long locationId \n    -String ipAddress \n    -String country \n    -String city \n    -String time \n    -String lat \n    -String lng \n    -Boolean isActive=false \n    -Date createdAt \n    -Date updatedAt \n    +getter-methods()\n    +setter-methods()\n    }\n\n\n","mermaid":"{\n  \"theme\": \"dark\"\n}","autoSync":true,"rough":false,"updateDiagram":true,"panZoom":false,"editorMode":"code"},"time":1733935543299,"type":"auto","id":"3f292e49-d05a-48b4-bc04-59d5409f4dcf","name":"tangy-oxygen"},{"state":{"code":"classDiagram\n    User <|-- UserDetails\n    User  \"1\" --> \"1\" Salary\n    class UserDetails{\n    -Long userId\n    -String firstName\n    -String lastName\n    -String jobTitle\n    -String license\n    -Gender gender\n    -String address\n    -String dateOfBirth\n    -Long totalFlightsHours\n    -Date createdAt\n    +getter-methods()\n    +setter-methods()\n    }\n    class User{\n        -Long userId\n        -String username\n        -String email\n        -String password\n        -Date createdAt\n        -Date updatedAt\n        +getter-methods()\n        +setter-methods()\n    }\n    class Salary{\n    -Long salaryId \n    -String degree \n    -Double basic \n    -Double bonus \n    -Double penalties \n    -Boolean availability \n    -Date createdAt \n    -Date updatedAt \n    +getter-methods()\n    +setter-methods()\n    }\n    class Location{\n    private Long locationId;\n    private String ipAddress;\n    private String country;\n    private String city;\n    private String time;\n    private String lat;\n    private String lng;\n    private Boolean isActive=false;\n    }\n\n\n","mermaid":"{\n  \"theme\": \"dark\"\n}","autoSync":true,"rough":false,"updateDiagram":true,"panZoom":false,"editorMode":"code"},"time":1733935483297,"type":"auto","id":"b092b1cd-4459-4623-b9fd-0c53667d5ae1","name":"cool-oyster"},{"state":{"code":"classDiagram\n    User <|-- UserDetails\n    User  \"1\" --> \"1\" Salary\n    class UserDetails{\n    -Long userId\n    -String firstName\n    -String lastName\n    -String jobTitle\n    -String license\n    -Gender gender\n    -String address\n    -String dateOfBirth\n    -Long totalFlightsHours\n    -Date createdAt\n    +getter-methods()\n    +setter-methods()\n    }\n    class User{\n        -Long userId\n        -String username\n        -String email\n        -String password\n        -Date createdAt\n        -Date updatedAt\n        +getter-methods()\n        +setter-methods()\n    }\n    class Salary{\n    -Long salaryId \n    -String degree \n    -Double basic \n    -Double bonus \n    -Double penalties \n    -Boolean availability \n    -Date createdAt \n    -Date updatedAt \n    +getter-met\n    }\n\n\n","mermaid":"{\n  \"theme\": \"dark\"\n}","autoSync":true,"rough":false,"updateDiagram":false,"panZoom":false,"editorMode":"code"},"time":1733935423297,"type":"auto","id":"a50958e7-a811-473c-832d-2ca49736cbbf","name":"tall-lock"},{"state":{"code":"classDiagram\n    User <|-- UserDetails\n    User -- Salary\n    class UserDetails{\n    -Long userId\n    -String firstName\n    -String lastName\n    -String jobTitle\n    -String license\n    -Gender gender\n    -String address\n    -String dateOfBirth\n    -Long totalFlightsHours\n    -Date createdAt\n    +getter-methods()\n    +setter-methods()\n    }\n    class User{\n        -Long userId\n        -String username\n        -String email\n        -String password\n        -Date createdAt\n        -Date updatedAt\n        +getter-methods()\n        +setter-methods()\n    }\n    class Salary{\n    -Long salaryId \n    -String degree \n    -Double basic \n    -Double bonus \n    -Double penalties \n    -Boolean availability \n    -Date createdAt \n    -Date updatedAt \n\n    }\n\n\n","mermaid":"{\n  \"theme\": \"dark\"\n}","autoSync":true,"rough":false,"updateDiagram":true,"panZoom":false,"editorMode":"code"},"time":1733935363298,"type":"auto","id":"c6515c21-34b1-4ae6-a4b8-e9fab9ad56b9","name":"odd-nurse"},{"state":{"code":"classDiagram\n    User <|-- UserDetails\n    User \n    class UserDetails{\n    -Long userId\n    -String firstName\n    -String lastName\n    -String jobTitle\n    -String license\n    -Gender gender\n    -String address\n    -String dateOfBirth\n    -Long totalFlightsHours\n    -Date createdAt\n    +getter-methods()\n    +setter-methods()\n    }\n    class User{\n        -Long userId\n        -String username\n        -String email\n        -String password\n        -Date createdAt\n        -Date updatedAt\n        +getter-methods()\n        +setter-methods()\n    }\n    class Salary{\n    -Long salaryId \n    -String degree \n    -Double basic \n    -Double bonus \n    -Double penalties \n    -Boolean availability \n    -Date createdAt \n    -Date updatedAt \n\n    }\n\n\n","mermaid":"{\n  \"theme\": \"dark\"\n}","autoSync":true,"rough":false,"updateDiagram":true,"panZoom":false,"editorMode":"code"},"time":1733935302716,"type":"auto","id":"2b869f9d-1675-414e-afa6-671aec0f0fcf","name":"brash-nest"},{"state":{"code":"classDiagram\n    User <|-- UserDetails\n\n    class UserDetails{\n    -Long userId\n    -String firstName\n    -String lastName\n    -String jobTitle\n    -String license\n    -Gender gender\n    -String address\n    -String dateOfBirth\n    -Long totalFlightsHours\n    -Date createdAt\n    +getter-methods()\n    +setter-methods()\n    }\n    class User{\n        -Long userId\n        -String username\n        -String email\n        -String password\n        -Date createdAt\n        -Date updatedAt\n        +getter-methods()\n        +setter-methods()\n    }\n    class Salary{\n    -Long salaryId \n    -String degree \n    -Double basic \n    -Double bonus \n    -Double penalties \n    -Boolean availability \n    -Date createdAt \n    -Date updatedAt \n    \n    }\n\n\n","mermaid":"{\n  \"theme\": \"dark\"\n}","autoSync":true,"rough":false,"updateDiagram":true,"panZoom":false,"editorMode":"code"},"time":1733935242716,"type":"auto","id":"e21c6840-7cae-4981-b0cb-6ed9a3c03257","name":"bland-monitor"},{"state":{"code":"classDiagram\n    User <|-- UserDetails\n\n    class UserDetails{\n    -Long userId\n    -String firstName\n    -String lastName\n    -String jobTitle\n    -String license\n    -Gender gender\n    -String address\n    -String dateOfBirth\n    -Long totalFlightsHours\n    -Date createdAt\n    +getter-methods()\n    +setter-methods()\n    }\n    class User{\n        -Long userId\n        -String username\n        -String email\n        -String password\n        -Date createdAt\n        -Date updatedAt\n        +getter-methods()\n        +setter-methods()\n    }\n    class Salary{\n    -Long salaryId \n    -String degree \n    -Double basic \n    -Double bonus \n    -Double penalties \n    -Boolean availability \n    -Date createdAt \n    -Date updatedAt \n    }\n\n","mermaid":"{\n  \"theme\": \"dark\"\n}","autoSync":true,"rough":false,"updateDiagram":true,"panZoom":false,"editorMode":"code"},"time":1733935122716,"type":"auto","id":"e3168c7f-afb3-4090-8f14-fe580bd8141a","name":"puny-intern"},{"state":{"code":"classDiagram\n    User <|-- UserDetails\n\n    class UserDetails{\n    -Long userId\n    -String firstName\n    -String lastName\n    -String jobTitle\n    -String license\n    -Gender gender\n    -String address\n    -String dateOfBirth\n    -Long totalFlightsHours\n    -Date createdAt\n    +getter-methods()\n    +setter-methods()\n    }\n    class User{\n        -Long userId\n        -String username\n        -String email\n        -String password\n        -Date createdAt\n        -Date updatedAt\n        +getter-methods()\n        +setter-methods()\n    }\n    class Salary{\n            \n    }\n\n","mermaid":"{\n  \"theme\": \"dark\"\n}","autoSync":true,"rough":false,"updateDiagram":true,"panZoom":false,"editorMode":"code"},"time":1733935062715,"type":"auto","id":"e86199b6-98d5-4f0d-a810-2117fe8516a7","name":"numerous-pizza"},{"state":{"code":"classDiagram\n    User <|-- UserDetails\n\n    class UserDetails{\n    -Long userId\n    -String firstName\n    -String lastName\n    -String jobTitle\n    -String license\n    -Gender gender\n    -String address\n    -String dateOfBirth\n    -Long totalFlightsHours\n    -Date createdAt\n    +getter-methods()\n    +setter-methods()\n    }\n    class User{\n        -Long userId\n        -String username\n        -String email\n        -String password\n        -Date createdAt\n        -Date updatedAt\n        +getter-methods()\n        +setter-methods()\n    }\n    class Salary{\n        \n    }\n\n","mermaid":"{\n  \"theme\": \"dark\"\n}","autoSync":true,"rough":false,"updateDiagram":false,"panZoom":false,"editorMode":"code"},"time":1733934582712,"type":"auto","id":"b55ce4cf-6428-40eb-b5cb-603ef96c05fc","name":"ugly-engine"},{"state":{"code":"classDiagram\n    User <|-- UserDetails\n\n    class UserDetails{\n    -Long userId\n    -String firstName\n    -String lastName\n    -String jobTitle\n    -String license\n    -Gender gender\n    -String address\n    -String dateOfBirth\n    -Long totalFlightsHours\n    -Date createdAt\n    +getter-methods()\n    +setter-methods()\n    }\n    class User{\n        -Long userId\n        -String username\n        -String email\n        -String password\n        -Date createdAt\n        -Date updatedAt\n        +getter-methods()\n        +setter-methods()\n    }\n    \n\n","mermaid":"{\n  \"theme\": \"dark\"\n}","autoSync":true,"rough":false,"updateDiagram":false,"panZoom":false,"editorMode":"code"},"time":1733934522711,"type":"auto","id":"001899d7-502a-4148-9a6f-78ebab8d48e6","name":"faithful-ambulance"},{"state":{"code":"classDiagram\n    User <|-- Duck\n    Animal <|-- Fish\n    Animal <|-- Zebra\n    Animal : +int age\n    Animal : +String gender\n    Animal: +isMammal()\n    Animal: +mate()\n    class UserDetails{\n    -Long userId\n    -String firstName\n    -String lastName\n    -String jobTitle\n    -String license\n    -Gender gender\n    -String address\n    -String dateOfBirth\n    -Long totalFlightsHours\n    -Date createdAt\n    +getter-methods()\n    +setter-methods()\n    }\n    class User{\n        -Long userId\n        -String username\n        -String email\n        -String password\n        -Date createdAt\n        -Date updatedAt\n        +getter-methods()\n        +setter-methods()\n    }\n\n","mermaid":"{\n  \"theme\": \"dark\"\n}","autoSync":true,"rough":false,"updateDiagram":true,"panZoom":false,"editorMode":"code"},"time":1733934462711,"type":"auto","id":"ac1156fc-9ca7-4950-ba9e-0864b19cf71d","name":"plump-park"},{"state":{"code":"classDiagram\n    Animal <|-- Duck\n    Animal <|-- Fish\n    Animal <|-- Zebra\n    Animal : +int age\n    Animal : +String gender\n    Animal: +isMammal()\n    Animal: +mate()\n    class UserDetails{\n    -Long userId\n    -String firstName\n    -String lastName\n    -String jobTitle\n    -String license\n    -Gender gender\n    -String address\n    -String dateOfBirth\n    -Long totalFlightsHours\n    -Date createdAt\n    +getter-methods()\n    +setter-methods()\n    }\n    class User{\n        -Long userId\n        -String username\n        -String email\n        -String password\n        -Date createdAt\n        -Date updatedAt\n        +getter-methods()\n        +setter-methods()\n    }\n    class Zebra{\n      +bool is_wild\n      +run()\n    }\n","mermaid":"{\n  \"theme\": \"dark\"\n}","autoSync":true,"rough":false,"updateDiagram":true,"panZoom":false},"time":1733934402536,"type":"auto","id":"4750cd55-5235-4d50-a7e4-90f15bfba77f","name":"teeny-balloon"},{"state":{"code":"classDiagram\n    Animal <|-- Duck\n    Animal <|-- Fish\n    Animal <|-- Zebra\n    Animal : +int age\n    Animal : +String gender\n    Animal: +isMammal()\n    Animal: +mate()\n    class UserDetails{\n    -Long userId\n    -String firstName\n    -String lastName\n    -String jobTitle\n    -String license\n    -Gender gender\n    -String address\n    -String dateOfBirth\n    -Long totalFlightsHours\n    +getter-methods()\n    +setter-methods()\n    }\n    class User{\n        -Long userId\n        -String username\n        -String email\n    }\n    class Zebra{\n      +bool is_wild\n      +run()\n    }\n","mermaid":"{\n  \"theme\": \"dark\"\n}","autoSync":true,"rough":false,"updateDiagram":true,"panZoom":false},"time":1733934342537,"type":"auto","id":"1bb118da-b443-492d-b658-3d1f5e271122","name":"some-nigeria"},{"state":{"code":"classDiagram\n    Animal <|-- Duck\n    Animal <|-- Fish\n    Animal <|-- Zebra\n    Animal : +int age\n    Animal : +String gender\n    Animal: +isMammal()\n    Animal: +mate()\n    class User{\n    -Long userId\n    -String firstName\n    -String lastName\n    -String jobTitle\n    -String license\n    -Gender gender\n    -String address\n    -String dateOfBirth\n    -Long totalFlightsHours\n    +getter-methods()\n    +setter-methods()\n    }\n    class UserDetails{\n      -int sizeInFeet\n      -canEat()\n    }\n    class Zebra{\n      +bool is_wild\n      +run()\n    }\n","mermaid":"{\n  \"theme\": \"dark\"\n}","autoSync":true,"rough":false,"updateDiagram":true,"panZoom":false},"time":1733934282536,"type":"auto","id":"15036ac8-afd7-4844-bdc1-c0123f6cef6a","name":"billowy-jackal"},{"state":{"code":"classDiagram\n    Animal <|-- Duck\n    Animal <|-- Fish\n    Animal <|-- Zebra\n    Animal : +int age\n    Animal : +String gender\n    Animal: +isMammal()\n    Animal: +mate()\n    class User{\n    -Long userId;\n    -String firstName;\n    -String lastName;\n    -String jobTitle;\n    -String license;\n    -Gender gender;\n    -String address;\n    -String dateOfBirth;\n    -Long totalFlightsHours;\n    +getter-m()\n    }\n    class Fish{\n      -int sizeInFeet\n      -canEat()\n    }\n    class Zebra{\n      +bool is_wild\n      +run()\n    }\n","mermaid":"{\n  \"theme\": \"dark\"\n}","autoSync":true,"rough":false,"updateDiagram":true,"panZoom":false},"time":1733934222536,"type":"auto","id":"4a4ddf91-7bf1-48ec-ac27-70f58a9ad51f","name":"spoiled-lizard"},{"state":{"code":"classDiagram\n    Animal <|-- Duck\n    Animal <|-- Fish\n    Animal <|-- Zebra\n    Animal : +int age\n    Animal : +String gender\n    Animal: +isMammal()\n    Animal: +mate()\n    class User{\n          private Long userId;\n    private String firstName;\n    private String lastName;\n    private String jobTitle;\n    @Column(nullable = false)\n    private String license;\n    private Gender gender;\n    private String address;\n    -String dateOfBirth;\n    -Long totalFlightsHours;\n\n    }\n    class Fish{\n      -int sizeInFeet\n      -canEat()\n    }\n    class Zebra{\n      +bool is_wild\n      +run()\n    }\n","mermaid":"{\n  \"theme\": \"dark\"\n}","autoSync":true,"rough":false,"updateDiagram":true,"panZoom":false},"time":1733934162535,"type":"auto","id":"44fa89af-12c0-43ba-9022-fd5d472f16f5","name":"nervous-dress"},{"state":{"code":"classDiagram\n    Animal <|-- Duck\n    Animal <|-- Fish\n    Animal <|-- Zebra\n    Animal : +int age\n    Animal : +String gender\n    Animal: +isMammal()\n    Animal: +mate()\n    class Duck{\n\n    }\n    class Fish{\n      -int sizeInFeet\n      -canEat()\n    }\n    class Zebra{\n      +bool is_wild\n      +run()\n    }\n","mermaid":"{\n  \"theme\": \"dark\"\n}","autoSync":true,"rough":false,"updateDiagram":false,"panZoom":false},"time":1733933682518,"type":"auto","id":"b73f42b2-3b66-43d0-b4c2-aecbb9c00e62","name":"lemon-state"}]